setup.py
src/zato/__init__.py
src/zato/redis_paginator/__init__.py
src/zato/redis_paginator/examples.py
src/zato_redis_paginator.egg-info/PKG-INFO
src/zato_redis_paginator.egg-info/SOURCES.txt
src/zato_redis_paginator.egg-info/dependency_links.txt
src/zato_redis_paginator.egg-info/namespace_packages.txt
src/zato_redis_paginator.egg-info/not-zip-safe
src/zato_redis_paginator.egg-info/requires.txt
src/zato_redis_paginator.egg-info/top_level.txt