Metadata-Version: 1.1
Name: zato-redis-paginator
Version: 1.0
Summary: Django-like pagination for Redis
Home-page: https://github.com/zatosource/zato-redis-paginator
Author: Zato Developers
Author-email: info@zato.io
License: BSD 3-Clause License
Keywords: redis pagination paginate django
Platform: OS Independent
Classifier: Development Status :: 5 - Production/Stable
Classifier: Environment :: Console
Classifier: Intended Audience :: Developers
Classifier: License :: OSI Approved :: BSD License
Classifier: Natural Language :: English
Classifier: Operating System :: OS Independent
Classifier: Operating System :: POSIX :: Linux
Classifier: Operating System :: MacOS :: MacOS X
Classifier: Programming Language :: Python
Classifier: Topic :: Communications
Classifier: Topic :: Software Development :: Libraries :: Python Modules
Classifier: Topic :: Software Development :: Object Brokering
